django_doctools-0.1.0.dist-info/licenses/LICENSE
doctools/__init__.py
doctools/admin.py
doctools/apps.py
doctools/constants.py
doctools/exceptions.py
doctools/models.py
doctools/parsers.py
doctools/processors.py
doctools/providers.py
doctools/urls.py
doctools/views.py
doctools/migrations/__init__.py
django_doctools-0.1.0.dist-info/METADATA
django_doctools-0.1.0.dist-info/WHEEL
django_doctools-0.1.0.dist-info/top_level.txt
django_doctools-0.1.0.dist-info/RECORD
