Metadata-Version: 2.4
Name: django-doctools
Version: 0.1.0
Summary: A Django app for AI-powered document processing
Home-page: https://github.com/yourusername/django-doctools
Author: Anshuman Saagar
Author-email: Your Name <your.email@example.com>
License: MIT
Classifier: Framework :: Django
Classifier: Programming Language :: Python :: 3
Classifier: License :: OSI Approved :: MIT License
Classifier: Operating System :: OS Independent
Requires-Python: >=3.10
License-File: LICENSE
Requires-Dist: Django>=3.2
Requires-Dist: google-generativeai>=0.3.0
Requires-Dist: python-docx>=0.8.11
Requires-Dist: pydantic>=2.0.0
Requires-Dist: boto3>=1.28.0
Requires-Dist: openai>=1.0.0
Requires-Dist: pillow>=11.1.0
Requires-Dist: pymupdf>=1.25.4
Provides-Extra: dev
Requires-Dist: pytest>=7.0.0; extra == "dev"
Requires-Dist: pytest-django>=4.5.2; extra == "dev"
Requires-Dist: black>=23.0.0; extra == "dev"
Requires-Dist: isort>=5.12.0; extra == "dev"
Requires-Dist: ruff>=0.0.261; extra == "dev"
Requires-Dist: mypy>=1.0.0; extra == "dev"
Dynamic: author
Dynamic: home-page
Dynamic: license-file
Dynamic: requires-python
